<?xml version="1.0" encoding="UTF-8" standalone="yes"?>
<c:chartSpace xmlns:c="http://schemas.openxmlformats.org/drawingml/2006/chart" xmlns:a="http://schemas.openxmlformats.org/drawingml/2006/main" xmlns:r="http://schemas.openxmlformats.org/officeDocument/2006/relationships"><c:date1904 val="0"/><c:lang val="en-US"/><c:roundedCorners val="0"/><mc:AlternateContent xmlns:mc="http://schemas.openxmlformats.org/markup-compatibility/2006"><mc:Choice Requires="c14" xmlns:c14="http://schemas.microsoft.com/office/drawing/2007/8/2/chart"><c14:style val="110"/></mc:Choice><mc:Fallback><c:style val="10"/></mc:Fallback></mc:AlternateContent><c:clrMapOvr bg1="lt1" tx1="dk1" bg2="lt2" tx2="dk2" accent1="accent1" accent2="accent2" accent3="accent3" accent4="accent4" accent5="accent5" accent6="accent6" hlink="hlink" folHlink="folHlink"/><c:chart><c:title><c:tx><c:rich><a:bodyPr/><a:lstStyle/><a:p><a:pPr><a:defRPr/></a:pPr><a:r><a:rPr lang="en-US" dirty="0"/><a:t>Linear </a:t></a:r><a:r><a:rPr lang="en-US" dirty="0" smtClean="0"/><a:t>Scale </a:t></a:r><a:r><a:rPr lang="en-US" dirty="0"/><a:t>by Year</a:t></a:r></a:p></c:rich></c:tx><c:overlay val="0"/></c:title><c:autoTitleDeleted val="0"/><c:plotArea><c:layout/><c:scatterChart><c:scatterStyle val="lineMarker"/><c:varyColors val="0"/><c:ser><c:idx val="0"/><c:order val="0"/><c:tx><c:v>Desktop</c:v></c:tx><c:spPr><a:ln w="47625"><a:noFill/></a:ln></c:spPr><c:xVal><c:numRef><c:f>'By Class'!$M$2:$M$42</c:f><c:numCache><c:formatCode>General</c:formatCode><c:ptCount val="41"/><c:pt idx="0"><c:v>1976.0</c:v></c:pt><c:pt idx="1"><c:v>1976.0</c:v></c:pt><c:pt idx="2"><c:v>1978.0</c:v></c:pt><c:pt idx="3"><c:v>1979.0</c:v></c:pt><c:pt idx="4"><c:v>1982.0</c:v></c:pt><c:pt idx="5"><c:v>1982.0</c:v></c:pt><c:pt idx="6"><c:v>1985.0</c:v></c:pt><c:pt idx="7"><c:v>1989.0</c:v></c:pt><c:pt idx="8"><c:v>1991.0</c:v></c:pt><c:pt idx="9"><c:v>1993.0</c:v></c:pt><c:pt idx="10"><c:v>1996.0</c:v></c:pt><c:pt idx="11"><c:v>1997.0</c:v></c:pt><c:pt idx="12"><c:v>1997.0</c:v></c:pt><c:pt idx="13"><c:v>1998.0</c:v></c:pt><c:pt idx="14"><c:v>1999.0</c:v></c:pt><c:pt idx="15"><c:v>1999.0</c:v></c:pt><c:pt idx="16"><c:v>1999.0</c:v></c:pt><c:pt idx="17"><c:v>1999.0</c:v></c:pt><c:pt idx="18"><c:v>2000.0</c:v></c:pt><c:pt idx="19"><c:v>2000.0</c:v></c:pt><c:pt idx="20"><c:v>2001.0</c:v></c:pt><c:pt idx="21"><c:v>2002.0</c:v></c:pt><c:pt idx="22"><c:v>2003.0</c:v></c:pt><c:pt idx="23"><c:v>2003.0</c:v></c:pt><c:pt idx="24"><c:v>2004.0</c:v></c:pt><c:pt idx="25"><c:v>2005.0</c:v></c:pt><c:pt idx="26"><c:v>2006.0</c:v></c:pt><c:pt idx="27"><c:v>2006.0</c:v></c:pt><c:pt idx="28"><c:v>2007.0</c:v></c:pt><c:pt idx="29"><c:v>2007.0</c:v></c:pt><c:pt idx="30"><c:v>2008.0</c:v></c:pt><c:pt idx="31" formatCode="0.00"><c:v>17.53563989299298</c:v></c:pt><c:pt idx="32" formatCode="0.00"><c:v>14.60964047443681</c:v></c:pt><c:pt idx="33" formatCode="0.00"><c:v>14.60964047443681</c:v></c:pt><c:pt idx="34"><c:v>2008.0</c:v></c:pt><c:pt idx="35"><c:v>2008.0</c:v></c:pt><c:pt idx="36"><c:v>2011.0</c:v></c:pt><c:pt idx="37"><c:v>2012.0</c:v></c:pt><c:pt idx="38"><c:v>2012.0</c:v></c:pt><c:pt idx="39"><c:v>2014.0</c:v></c:pt><c:pt idx="40"><c:v>2015.0</c:v></c:pt></c:numCache></c:numRef></c:xVal><c:yVal><c:numRef><c:f>'By Class'!$R$2:$R$42</c:f><c:numCache><c:formatCode>0</c:formatCode><c:ptCount val="41"/><c:pt idx="0"><c:v>55470.01962252291</c:v></c:pt><c:pt idx="1"><c:v>46017.89933084222</c:v></c:pt><c:pt idx="2"><c:v>33733.23338316008</c:v></c:pt><c:pt idx="3"><c:v>25437.35095345842</c:v></c:pt><c:pt idx="4"><c:v>33028.91295379081</c:v></c:pt><c:pt idx="5"><c:v>19122.54276478536</c:v></c:pt><c:pt idx="6"><c:v>19446.89739217591</c:v></c:pt><c:pt idx="7"><c:v>12107.06312518397</c:v></c:pt><c:pt idx="8"><c:v>12560.96245427785</c:v></c:pt><c:pt idx="9"><c:v>9738.5168109635</c:v></c:pt><c:pt idx="10"><c:v>7640.163154230138</c:v></c:pt><c:pt idx="11"><c:v>5099.019513592784</c:v></c:pt><c:pt idx="12"><c:v>4290.581651605165</c:v></c:pt><c:pt idx="13"><c:v>3881.580434135903</c:v></c:pt><c:pt idx="14"><c:v>3670.651741928988</c:v></c:pt><c:pt idx="15"><c:v>2563.072973150283</c:v></c:pt><c:pt idx="16"><c:v>2353.70051265797</c:v></c:pt><c:pt idx="17"><c:v>2891.995221924885</c:v></c:pt><c:pt idx="18"><c:v>1951.800145897066</c:v></c:pt><c:pt idx="19"><c:v>2273.030282830976</c:v></c:pt><c:pt idx="20"><c:v>1341.640786499874</c:v></c:pt><c:pt idx="21"><c:v>1623.688281771977</c:v></c:pt><c:pt idx="22"><c:v>1363.831673049326</c:v></c:pt><c:pt idx="23"><c:v>1349.990382227133</c:v></c:pt><c:pt idx="24"><c:v>991.0312089651144</c:v></c:pt><c:pt idx="25"><c:v>919.8662110077973</c:v></c:pt><c:pt idx="26"><c:v>699.3786061802354</c:v></c:pt><c:pt idx="27"><c:v>701.0056595405658</c:v></c:pt><c:pt idx="28"><c:v>810.4349040655952</c:v></c:pt><c:pt idx="29"><c:v>510.2358597780112</c:v></c:pt><c:pt idx="30"><c:v>600.7242006257042</c:v></c:pt><c:pt idx="31"><c:v>21151.08557622118</c:v></c:pt><c:pt idx="32"><c:v>44721.3595499958</c:v></c:pt><c:pt idx="33"><c:v>34641.01615137754</c:v></c:pt><c:pt idx="34"><c:v>599.8175737264004</c:v></c:pt><c:pt idx="35"><c:v>583.4118555016188</c:v></c:pt><c:pt idx="36"><c:v>431.5169713368457</c:v></c:pt><c:pt idx="37"><c:v>434.5055675798257</c:v></c:pt><c:pt idx="38"><c:v>338.0617018914066</c:v></c:pt><c:pt idx="39"><c:v>355.5679561329612</c:v></c:pt><c:pt idx="40"><c:v>264.575131106459</c:v></c:pt></c:numCache></c:numRef></c:yVal><c:smooth val="0"/></c:ser><c:ser><c:idx val="1"/><c:order val="1"/><c:tx><c:v>Embedded</c:v></c:tx><c:spPr><a:ln w="47625"><a:noFill/></a:ln></c:spPr><c:xVal><c:numRef><c:f>'By Class'!$M$43:$M$55</c:f><c:numCache><c:formatCode>0.00</c:formatCode><c:ptCount val="13"/><c:pt idx="0" formatCode="General"><c:v>1971.0</c:v></c:pt><c:pt idx="1"><c:v>24.5754247590989</c:v></c:pt><c:pt idx="2"><c:v>31.48231535470742</c:v></c:pt><c:pt idx="3" formatCode="General"><c:v>1972.0</c:v></c:pt><c:pt idx="4" formatCode="General"><c:v>1974.0</c:v></c:pt><c:pt idx="5" formatCode="General"><c:v>1974.0</c:v></c:pt><c:pt idx="6" formatCode="General"><c:v>1974.0</c:v></c:pt><c:pt idx="7" formatCode="General"><c:v>1975.0</c:v></c:pt><c:pt idx="8" formatCode="General"><c:v>1978.0</c:v></c:pt><c:pt idx="9" formatCode="General"><c:v>1981.0</c:v></c:pt><c:pt idx="10" formatCode="General"><c:v>2008.0</c:v></c:pt><c:pt idx="11" formatCode="General"><c:v>2013.0</c:v></c:pt><c:pt idx="12" formatCode="General"><c:v>2014.0</c:v></c:pt></c:numCache></c:numRef></c:xVal><c:yVal><c:numRef><c:f>'By Class'!$R$43:$R$55</c:f><c:numCache><c:formatCode>0</c:formatCode><c:ptCount val="13"/><c:pt idx="0"><c:v>72231.51185146139</c:v></c:pt><c:pt idx="1"><c:v>1414.213562373095</c:v></c:pt><c:pt idx="2"><c:v>206.5591117977289</c:v></c:pt><c:pt idx="3"><c:v>63245.55320336758</c:v></c:pt><c:pt idx="4"><c:v>62469.50475544243</c:v></c:pt><c:pt idx="5"><c:v>66666.66666666667</c:v></c:pt><c:pt idx="6"><c:v>73484.69228349534</c:v></c:pt><c:pt idx="7"><c:v>77349.24681537577</c:v></c:pt><c:pt idx="8"><c:v>48304.58915396479</c:v></c:pt><c:pt idx="9"><c:v>22841.60962880627</c:v></c:pt><c:pt idx="10"><c:v>714.5896010104963</c:v></c:pt><c:pt idx="11"><c:v>319.3743884534262</c:v></c:pt><c:pt idx="12"><c:v>210.9502310972898</c:v></c:pt></c:numCache></c:numRef></c:yVal><c:smooth val="0"/></c:ser><c:ser><c:idx val="2"/><c:order val="2"/><c:tx><c:v>GPU</c:v></c:tx><c:spPr><a:ln w="47625"><a:noFill/></a:ln></c:spPr><c:marker><c:spPr><a:solidFill><a:srgbClr val="FFFF00"/></a:solidFill></c:spPr></c:marker><c:xVal><c:numRef><c:f>'By Class'!$M$56:$M$89</c:f><c:numCache><c:formatCode>General</c:formatCode><c:ptCount val="34"/><c:pt idx="0"><c:v>1997.0</c:v></c:pt><c:pt idx="1"><c:v>1999.0</c:v></c:pt><c:pt idx="2"><c:v>1999.0</c:v></c:pt><c:pt idx="3"><c:v>2000.0</c:v></c:pt><c:pt idx="4"><c:v>2000.0</c:v></c:pt><c:pt idx="5"><c:v>2000.0</c:v></c:pt><c:pt idx="6"><c:v>2001.0</c:v></c:pt><c:pt idx="7"><c:v>2001.0</c:v></c:pt><c:pt idx="8"><c:v>2002.0</c:v></c:pt><c:pt idx="9"><c:v>2002.0</c:v></c:pt><c:pt idx="10"><c:v>2003.0</c:v></c:pt><c:pt idx="11"><c:v>2003.0</c:v></c:pt><c:pt idx="12"><c:v>2004.0</c:v></c:pt><c:pt idx="13"><c:v>2004.0</c:v></c:pt><c:pt idx="14"><c:v>2005.0</c:v></c:pt><c:pt idx="15"><c:v>2005.0</c:v></c:pt><c:pt idx="16"><c:v>2006.0</c:v></c:pt><c:pt idx="17"><c:v>2006.0</c:v></c:pt><c:pt idx="18"><c:v>2006.0</c:v></c:pt><c:pt idx="19"><c:v>2007.0</c:v></c:pt><c:pt idx="20"><c:v>2007.0</c:v></c:pt><c:pt idx="21"><c:v>2008.0</c:v></c:pt><c:pt idx="22"><c:v>2008.0</c:v></c:pt><c:pt idx="23"><c:v>2009.0</c:v></c:pt><c:pt idx="24"><c:v>2010.0</c:v></c:pt><c:pt idx="25"><c:v>2010.0</c:v></c:pt><c:pt idx="26"><c:v>2010.0</c:v></c:pt><c:pt idx="27"><c:v>2011.0</c:v></c:pt><c:pt idx="28"><c:v>2012.0</c:v></c:pt><c:pt idx="29"><c:v>2012.0</c:v></c:pt><c:pt idx="30"><c:v>2013.0</c:v></c:pt><c:pt idx="31"><c:v>2013.0</c:v></c:pt><c:pt idx="32"><c:v>2014.0</c:v></c:pt><c:pt idx="33"><c:v>2015.0</c:v></c:pt></c:numCache></c:numRef></c:xVal><c:yVal><c:numRef><c:f>'By Class'!$R$56:$R$89</c:f><c:numCache><c:formatCode>0</c:formatCode><c:ptCount val="34"/><c:pt idx="0"><c:v>5070.9255283711</c:v></c:pt><c:pt idx="1"><c:v>2958.039891549808</c:v></c:pt><c:pt idx="2"><c:v>2196.83566898431</c:v></c:pt><c:pt idx="3"><c:v>1802.775637731994</c:v></c:pt><c:pt idx="4"><c:v>1800.0</c:v></c:pt><c:pt idx="5"><c:v>1798.147194568157</c:v></c:pt><c:pt idx="6"><c:v>1498.53729853071</c:v></c:pt><c:pt idx="7"><c:v>1064.581294844754</c:v></c:pt><c:pt idx="8"><c:v>1501.322168612804</c:v></c:pt><c:pt idx="9"><c:v>1427.369320663049</c:v></c:pt><c:pt idx="10"><c:v>1365.008374790376</c:v></c:pt><c:pt idx="11"><c:v>1238.278374733781</c:v></c:pt><c:pt idx="12"><c:v>1362.442659343871</c:v></c:pt><c:pt idx="13"><c:v>1172.123659804661</c:v></c:pt><c:pt idx="14"><c:v>1048.336730726392</c:v></c:pt><c:pt idx="15"><c:v>947.20444555663</c:v></c:pt><c:pt idx="16"><c:v>957.6076692115514</c:v></c:pt><c:pt idx="17"><c:v>957.427107756338</c:v></c:pt><c:pt idx="18"><c:v>839.550960322227</c:v></c:pt><c:pt idx="19"><c:v>774.5966692414833</c:v></c:pt><c:pt idx="20"><c:v>655.521336656307</c:v></c:pt><c:pt idx="21"><c:v>542.2695903836474</c:v></c:pt><c:pt idx="22"><c:v>641.4269805898184</c:v></c:pt><c:pt idx="23"><c:v>393.7770344140711</c:v></c:pt><c:pt idx="24"><c:v>383.8599807852921</c:v></c:pt><c:pt idx="25"><c:v>405.4318685056712</c:v></c:pt><c:pt idx="26"><c:v>416.3331998932265</c:v></c:pt><c:pt idx="27"><c:v>290.9184131623206</c:v></c:pt><c:pt idx="28"><c:v>288.1854393574164</c:v></c:pt><c:pt idx="29"><c:v>281.4911866037607</c:v></c:pt><c:pt idx="30"><c:v>269.4438717061496</c:v></c:pt><c:pt idx="31"><c:v>263.673679998231</c:v></c:pt><c:pt idx="32"><c:v>276.6558539746838</c:v></c:pt><c:pt idx="33"><c:v>272.3922371584719</c:v></c:pt></c:numCache></c:numRef></c:yVal><c:smooth val="0"/></c:ser><c:ser><c:idx val="3"/><c:order val="3"/><c:tx><c:v>Server</c:v></c:tx><c:spPr><a:ln w="47625"><a:noFill/></a:ln></c:spPr><c:xVal><c:numRef><c:f>'By Class'!$M$90:$M$117</c:f><c:numCache><c:formatCode>General</c:formatCode><c:ptCount val="28"/><c:pt idx="0"><c:v>1995.0</c:v></c:pt><c:pt idx="1"><c:v>2002.0</c:v></c:pt><c:pt idx="2"><c:v>2003.0</c:v></c:pt><c:pt idx="3"><c:v>2004.0</c:v></c:pt><c:pt idx="4"><c:v>2006.0</c:v></c:pt><c:pt idx="5"><c:v>2007.0</c:v></c:pt><c:pt idx="6"><c:v>2007.0</c:v></c:pt><c:pt idx="7"><c:v>2008.0</c:v></c:pt><c:pt idx="8"><c:v>2009.0</c:v></c:pt><c:pt idx="9"><c:v>2010.0</c:v></c:pt><c:pt idx="10"><c:v>2010.0</c:v></c:pt><c:pt idx="11"><c:v>2010.0</c:v></c:pt><c:pt idx="12"><c:v>2010.0</c:v></c:pt><c:pt idx="13"><c:v>2010.0</c:v></c:pt><c:pt idx="14"><c:v>2010.0</c:v></c:pt><c:pt idx="15"><c:v>2011.0</c:v></c:pt><c:pt idx="16"><c:v>2011.0</c:v></c:pt><c:pt idx="17"><c:v>2012.0</c:v></c:pt><c:pt idx="18"><c:v>2012.0</c:v></c:pt><c:pt idx="19"><c:v>2012.0</c:v></c:pt><c:pt idx="20"><c:v>2012.0</c:v></c:pt><c:pt idx="21"><c:v>2013.0</c:v></c:pt><c:pt idx="22"><c:v>2013.0</c:v></c:pt><c:pt idx="23"><c:v>2014.0</c:v></c:pt><c:pt idx="24"><c:v>2014.0</c:v></c:pt><c:pt idx="25" formatCode="0.00"><c:v>32.21928094887362</c:v></c:pt><c:pt idx="26"><c:v>2014.0</c:v></c:pt><c:pt idx="27"><c:v>2015.0</c:v></c:pt></c:numCache></c:numRef></c:xVal><c:yVal><c:numRef><c:f>'By Class'!$R$90:$R$117</c:f><c:numCache><c:formatCode>0</c:formatCode><c:ptCount val="28"/><c:pt idx="0"><c:v>7471.15665865613</c:v></c:pt><c:pt idx="1"><c:v>1383.342460721987</c:v></c:pt><c:pt idx="2"><c:v>955.0890649312343</c:v></c:pt><c:pt idx="3"><c:v>854.2421961772491</c:v></c:pt><c:pt idx="4"><c:v>592.1049191605468</c:v></c:pt><c:pt idx="5"><c:v>781.8127023219029</c:v></c:pt><c:pt idx="6"><c:v>657.4136056720206</c:v></c:pt><c:pt idx="7"><c:v>514.525842018905</c:v></c:pt><c:pt idx="8"><c:v>618.6625597463114</c:v></c:pt><c:pt idx="9"><c:v>614.00325732035</c:v></c:pt><c:pt idx="10"><c:v>452.9108136578383</c:v></c:pt><c:pt idx="11"><c:v>687.386354243376</c:v></c:pt><c:pt idx="12"><c:v>604.7431568147629</c:v></c:pt><c:pt idx="13"><c:v>591.185250154298</c:v></c:pt><c:pt idx="14"><c:v>545.3359554878314</c:v></c:pt><c:pt idx="15"><c:v>437.2521324279338</c:v></c:pt><c:pt idx="16"><c:v>443.7601569801817</c:v></c:pt><c:pt idx="17"><c:v>512.347538297978</c:v></c:pt><c:pt idx="18"><c:v>519.6152422706635</c:v></c:pt><c:pt idx="19"><c:v>465.9301547344936</c:v></c:pt><c:pt idx="20"><c:v>418.9079504709142</c:v></c:pt><c:pt idx="21"><c:v>370.9911166081326</c:v></c:pt><c:pt idx="22"><c:v>393.3978962347215</c:v></c:pt><c:pt idx="23"><c:v>369.5111115223215</c:v></c:pt><c:pt idx="24"><c:v>354.2908999160732</c:v></c:pt><c:pt idx="25"><c:v>328.9376840679705</c:v></c:pt><c:pt idx="26"><c:v>344.7968852619335</c:v></c:pt><c:pt idx="27"><c:v>412.2193736714411</c:v></c:pt></c:numCache></c:numRef></c:yVal><c:smooth val="0"/></c:ser><c:ser><c:idx val="4"/><c:order val="4"/><c:tx><c:v>Trend</c:v></c:tx><c:marker><c:symbol val="none"/></c:marker><c:xVal><c:numRef><c:f>'By Class'!$A$122:$A$123</c:f><c:numCache><c:formatCode>General</c:formatCode><c:ptCount val="2"/><c:pt idx="0"><c:v>1970.0</c:v></c:pt><c:pt idx="1"><c:v>2015.0</c:v></c:pt></c:numCache></c:numRef></c:xVal><c:yVal><c:numRef><c:f>'By Class'!$I$122:$I$123</c:f><c:numCache><c:formatCode>0.000</c:formatCode><c:ptCount val="2"/><c:pt idx="0"><c:v>135981.0098517835</c:v></c:pt><c:pt idx="1"><c:v>250.6697821199649</c:v></c:pt></c:numCache></c:numRef></c:yVal><c:smooth val="0"/></c:ser><c:dLbls><c:showLegendKey val="0"/><c:showVal val="0"/><c:showCatName val="0"/><c:showSerName val="0"/><c:showPercent val="0"/><c:showBubbleSize val="0"/></c:dLbls><c:axId val="-2127623480"/><c:axId val="-2128019624"/></c:scatterChart><c:valAx><c:axId val="-2127623480"/><c:scaling><c:orientation val="minMax"/><c:max val="2015.0"/><c:min val="1970.0"/></c:scaling><c:delete val="0"/><c:axPos val="b"/><c:title><c:tx><c:rich><a:bodyPr/><a:lstStyle/><a:p><a:pPr><a:defRPr/></a:pPr><a:r><a:rPr lang="en-US"/><a:t>Year</a:t></a:r></a:p></c:rich></c:tx><c:overlay val="0"/></c:title><c:numFmt formatCode="General" sourceLinked="1"/><c:majorTickMark val="cross"/><c:minorTickMark val="cross"/><c:tickLblPos val="nextTo"/><c:crossAx val="-2128019624"/><c:crosses val="autoZero"/><c:crossBetween val="midCat"/></c:valAx><c:valAx><c:axId val="-2128019624"/><c:scaling><c:logBase val="10.0"/><c:orientation val="minMax"/><c:max val="1.0E6"/><c:min val="1.0"/></c:scaling><c:delete val="0"/><c:axPos val="l"/><c:majorGridlines/><c:title><c:tx><c:rich><a:bodyPr/><a:lstStyle/><a:p><a:pPr><a:defRPr/></a:pPr><a:r><a:rPr lang="en-US"/><a:t>Sqrt(A/N) (nm)</a:t></a:r></a:p></c:rich></c:tx><c:overlay val="0"/></c:title><c:numFmt formatCode="#,##0" sourceLinked="0"/><c:majorTickMark val="none"/><c:minorTickMark val="none"/><c:tickLblPos val="nextTo"/><c:crossAx val="-2127623480"/><c:crosses val="autoZero"/><c:crossBetween val="midCat"/><c:minorUnit val="10.0"/></c:valAx></c:plotArea><c:legend><c:legendPos val="r"/><c:overlay val="0"/></c:legend><c:plotVisOnly val="1"/><c:dispBlanksAs val="gap"/><c:showDLblsOverMax val="0"/></c:chart><c:txPr><a:bodyPr/><a:lstStyle/><a:p><a:pPr><a:defRPr sz="1800"/></a:pPr><a:endParaRPr lang="en-US"/></a:p></c:txPr><c:externalData r:id="rId2"><c:autoUpdate val="0"/></c:externalData></c:chartSpace>