<?xml version="1.0" encoding="UTF-8" standalone="yes"?>
<p:sld xmlns:a="http://schemas.openxmlformats.org/drawingml/2006/main" xmlns:r="http://schemas.openxmlformats.org/officeDocument/2006/relationships" xmlns:p="http://schemas.openxmlformats.org/presentationml/2006/main"><p:cSld><p:spTree><p:nvGrpSpPr><p:cNvPr id="1" name=""/><p:cNvGrpSpPr/><p:nvPr/></p:nvGrpSpPr><p:grpSpPr><a:xfrm><a:off x="0" y="0"/><a:ext cx="0" cy="0"/><a:chOff x="0" y="0"/><a:chExt cx="0" cy="0"/></a:xfrm></p:grpSpPr><p:sp><p:nvSpPr><p:cNvPr id="5" name="Title 4"/><p:cNvSpPr><a:spLocks noGrp="1"/></p:cNvSpPr><p:nvPr><p:ph type="title"/></p:nvPr></p:nvSpPr><p:spPr/><p:txBody><a:bodyPr/><a:lstStyle/><a:p><a:r><a:rPr lang="en-US" dirty="0" smtClean="0"/><a:t>Final Thoughts</a:t></a:r><a:endParaRPr lang="en-US" dirty="0"/></a:p></p:txBody></p:sp><p:sp><p:nvSpPr><p:cNvPr id="6" name="Content Placeholder 5"/><p:cNvSpPr><a:spLocks noGrp="1"/></p:cNvSpPr><p:nvPr><p:ph idx="1"/></p:nvPr></p:nvSpPr><p:spPr/><p:txBody><a:bodyPr/><a:lstStyle/><a:p><a:r><a:rPr lang="en-US" dirty="0" smtClean="0"/><a:t>Compared to future, past 50 years will seem fairly straightforward</a:t></a:r></a:p><a:p><a:pPr lvl="1"/><a:r><a:rPr lang="en-US" dirty="0"/><a:t>50 years of using photolithography to pattern transistors on two-dimensional </a:t></a:r><a:r><a:rPr lang="en-US" dirty="0" smtClean="0"/><a:t>surface</a:t></a:r><a:endParaRPr lang="en-US" dirty="0"/></a:p><a:p><a:r><a:rPr lang="en-US" dirty="0" smtClean="0"/><a:t>Questions about future integrated systems</a:t></a:r></a:p><a:p><a:pPr lvl="1"/><a:r><a:rPr lang="en-US" dirty="0" smtClean="0"/><a:t>Can we build them?</a:t></a:r></a:p><a:p><a:pPr lvl="1"/><a:r><a:rPr lang="en-US" dirty="0" smtClean="0"/><a:t>What will be the technology?</a:t></a:r></a:p><a:p><a:pPr lvl="1"/><a:r><a:rPr lang="en-US" dirty="0" smtClean="0"/><a:t>Are they commercially viable?</a:t></a:r></a:p><a:p><a:pPr lvl="1"/><a:r><a:rPr lang="en-US" dirty="0" smtClean="0"/><a:t>Can we keep power consumption low?</a:t></a:r></a:p><a:p><a:pPr lvl="1"/><a:r><a:rPr lang="en-US" dirty="0" smtClean="0"/><a:t>What will we do with them?</a:t></a:r></a:p><a:p><a:pPr lvl="1"/><a:r><a:rPr lang="en-US" dirty="0" smtClean="0"/><a:t>How will we program / customize them?</a:t></a:r></a:p><a:p><a:pPr lvl="1"/><a:endParaRPr lang="en-US" dirty="0" smtClean="0"/></a:p><a:p><a:endParaRPr lang="en-US" dirty="0"/></a:p></p:txBody></p:sp></p:spTree><p:extLst><p:ext uri="{BB962C8B-B14F-4D97-AF65-F5344CB8AC3E}"><p14:creationId xmlns:p14="http://schemas.microsoft.com/office/powerpoint/2010/main" val="1882219158"/></p:ext></p:extLst></p:cSld><p:clrMapOvr><a:masterClrMapping/></p:clrMapOvr><mc:AlternateContent xmlns:mc="http://schemas.openxmlformats.org/markup-compatibility/2006" xmlns:p14="http://schemas.microsoft.com/office/powerpoint/2010/main"><mc:Choice Requires="p14"><p:transition spd="slow" p14:dur="2000"/></mc:Choice><mc:Fallback xmlns=""><p:transition spd="slow" xmlns:p14="http://schemas.microsoft.com/office/powerpoint/2010/main"/></mc:Fallback></mc:AlternateContent><p:timing><p:tnLst><p:par><p:cTn id="1" dur="indefinite" restart="never" nodeType="tmRoot" xmlns:p14="http://schemas.microsoft.com/office/powerpoint/2010/main"><p:childTnLst><p:seq concurrent="1" nextAc="seek"><p:cTn id="2" dur="indefinite" nodeType="mainSeq"><p:childTnLst><p:par><p:cTn id="3" fill="hold"><p:stCondLst><p:cond delay="indefinite"/></p:stCondLst><p:childTnLst><p:par><p:cTn id="4" fill="hold"><p:stCondLst><p:cond delay="0"/></p:stCondLst><p:childTnLst><p:par><p:cTn id="5" presetID="1" presetClass="entr" presetSubtype="0" fill="hold" grpId="0" nodeType="clickEffect"><p:stCondLst><p:cond delay="0"/></p:stCondLst><p:childTnLst><p:set><p:cBhvr><p:cTn id="6" dur="1" fill="hold"><p:stCondLst><p:cond delay="0"/></p:stCondLst></p:cTn><p:tgtEl><p:spTgt spid="6"><p:txEl><p:pRg st="0" end="0"/></p:txEl></p:spTgt></p:tgtEl><p:attrNameLst><p:attrName>style.visibility</p:attrName></p:attrNameLst></p:cBhvr><p:to><p:strVal val="visible"/></p:to></p:set></p:childTnLst></p:cTn></p:par><p:par><p:cTn id="7" presetID="1" presetClass="entr" presetSubtype="0" fill="hold" grpId="0" nodeType="withEffect"><p:stCondLst><p:cond delay="0"/></p:stCondLst><p:childTnLst><p:set><p:cBhvr><p:cTn id="8" dur="1" fill="hold"><p:stCondLst><p:cond delay="0"/></p:stCondLst></p:cTn><p:tgtEl><p:spTgt spid="6"><p:txEl><p:pRg st="1" end="1"/></p:txEl></p:spTgt></p:tgtEl><p:attrNameLst><p:attrName>style.visibility</p:attrName></p:attrNameLst></p:cBhvr><p:to><p:strVal val="visible"/></p:to></p:set></p:childTnLst></p:cTn></p:par></p:childTnLst></p:cTn></p:par></p:childTnLst></p:cTn></p:par><p:par><p:cTn id="9" fill="hold"><p:stCondLst><p:cond delay="indefinite"/></p:stCondLst><p:childTnLst><p:par><p:cTn id="10" fill="hold"><p:stCondLst><p:cond delay="0"/></p:stCondLst><p:childTnLst><p:par><p:cTn id="11" presetID="1" presetClass="entr" presetSubtype="0" fill="hold" grpId="0" nodeType="clickEffect"><p:stCondLst><p:cond delay="0"/></p:stCondLst><p:childTnLst><p:set><p:cBhvr><p:cTn id="12" dur="1" fill="hold"><p:stCondLst><p:cond delay="0"/></p:stCondLst></p:cTn><p:tgtEl><p:spTgt spid="6"><p:txEl><p:pRg st="2" end="2"/></p:txEl></p:spTgt></p:tgtEl><p:attrNameLst><p:attrName>style.visibility</p:attrName></p:attrNameLst></p:cBhvr><p:to><p:strVal val="visible"/></p:to></p:set></p:childTnLst></p:cTn></p:par><p:par><p:cTn id="13" presetID="1" presetClass="entr" presetSubtype="0" fill="hold" grpId="0" nodeType="withEffect"><p:stCondLst><p:cond delay="0"/></p:stCondLst><p:childTnLst><p:set><p:cBhvr><p:cTn id="14" dur="1" fill="hold"><p:stCondLst><p:cond delay="0"/></p:stCondLst></p:cTn><p:tgtEl><p:spTgt spid="6"><p:txEl><p:pRg st="3" end="3"/></p:txEl></p:spTgt></p:tgtEl><p:attrNameLst><p:attrName>style.visibility</p:attrName></p:attrNameLst></p:cBhvr><p:to><p:strVal val="visible"/></p:to></p:set></p:childTnLst></p:cTn></p:par><p:par><p:cTn id="15" presetID="1" presetClass="entr" presetSubtype="0" fill="hold" grpId="0" nodeType="withEffect"><p:stCondLst><p:cond delay="0"/></p:stCondLst><p:childTnLst><p:set><p:cBhvr><p:cTn id="16" dur="1" fill="hold"><p:stCondLst><p:cond delay="0"/></p:stCondLst></p:cTn><p:tgtEl><p:spTgt spid="6"><p:txEl><p:pRg st="4" end="4"/></p:txEl></p:spTgt></p:tgtEl><p:attrNameLst><p:attrName>style.visibility</p:attrName></p:attrNameLst></p:cBhvr><p:to><p:strVal val="visible"/></p:to></p:set></p:childTnLst></p:cTn></p:par><p:par><p:cTn id="17" presetID="1" presetClass="entr" presetSubtype="0" fill="hold" grpId="0" nodeType="withEffect"><p:stCondLst><p:cond delay="0"/></p:stCondLst><p:childTnLst><p:set><p:cBhvr><p:cTn id="18" dur="1" fill="hold"><p:stCondLst><p:cond delay="0"/></p:stCondLst></p:cTn><p:tgtEl><p:spTgt spid="6"><p:txEl><p:pRg st="5" end="5"/></p:txEl></p:spTgt></p:tgtEl><p:attrNameLst><p:attrName>style.visibility</p:attrName></p:attrNameLst></p:cBhvr><p:to><p:strVal val="visible"/></p:to></p:set></p:childTnLst></p:cTn></p:par><p:par><p:cTn id="19" presetID="1" presetClass="entr" presetSubtype="0" fill="hold" grpId="0" nodeType="withEffect"><p:stCondLst><p:cond delay="0"/></p:stCondLst><p:childTnLst><p:set><p:cBhvr><p:cTn id="20" dur="1" fill="hold"><p:stCondLst><p:cond delay="0"/></p:stCondLst></p:cTn><p:tgtEl><p:spTgt spid="6"><p:txEl><p:pRg st="6" end="6"/></p:txEl></p:spTgt></p:tgtEl><p:attrNameLst><p:attrName>style.visibility</p:attrName></p:attrNameLst></p:cBhvr><p:to><p:strVal val="visible"/></p:to></p:set></p:childTnLst></p:cTn></p:par><p:par><p:cTn id="21" presetID="1" presetClass="entr" presetSubtype="0" fill="hold" grpId="0" nodeType="withEffect"><p:stCondLst><p:cond delay="0"/></p:stCondLst><p:childTnLst><p:set><p:cBhvr><p:cTn id="22" dur="1" fill="hold"><p:stCondLst><p:cond delay="0"/></p:stCondLst></p:cTn><p:tgtEl><p:spTgt spid="6"><p:txEl><p:pRg st="7" end="7"/></p:txEl></p:spTgt></p:tgtEl><p:attrNameLst><p:attrName>style.visibility</p:attrName></p:attrNameLst></p:cBhvr><p:to><p:strVal val="visible"/></p:to></p:set></p:childTnLst></p:cTn></p:par><p:par><p:cTn id="23" presetID="1" presetClass="entr" presetSubtype="0" fill="hold" grpId="0" nodeType="withEffect"><p:stCondLst><p:cond delay="0"/></p:stCondLst><p:childTnLst><p:set><p:cBhvr><p:cTn id="24" dur="1" fill="hold"><p:stCondLst><p:cond delay="0"/></p:stCondLst></p:cTn><p:tgtEl><p:spTgt spid="6"><p:txEl><p:pRg st="8" end="8"/></p:txEl></p:spTgt></p:tgtEl><p:attrNameLst><p:attrName>style.visibility</p:attrName></p:attrNameLst></p:cBhvr><p:to><p:strVal val="visible"/></p:to></p:set></p:childTnLst></p:cTn></p:par></p:childTnLst></p:cTn></p:par></p:childTnLst></p:cTn></p:par></p:childTnLst></p:cTn><p:prevCondLst><p:cond evt="onPrev" delay="0"><p:tgtEl><p:sldTgt/></p:tgtEl></p:cond></p:prevCondLst><p:nextCondLst><p:cond evt="onNext" delay="0"><p:tgtEl><p:sldTgt/></p:tgtEl></p:cond></p:nextCondLst></p:seq></p:childTnLst></p:cTn></p:par></p:tnLst><p:bldLst><p:bldP spid="6" grpId="0" build="p"/></p:bldLst></p:timing></p:sld>